oqtant/__init__.py
oqtant/fixtures/__init__.py
oqtant/fixtures/jobs.py
oqtant/oqtant_client.py
oqtant/schemas/__init__.py
oqtant/schemas/job.py
oqtant/schemas/optical.py
oqtant/schemas/output.py
oqtant/schemas/quantum_matter.py
oqtant/schemas/rf.py
oqtant/settings.py
oqtant/simulator/README.md
oqtant/simulator/__init__.py
oqtant/simulator/qm_potential.py
oqtant/simulator/simulator.py
oqtant/simulator/three_dim.py
oqtant/simulator/wave_function.py
oqtant/start_notebook.py
oqtant/util/__init__.py
oqtant/util/auth.py
oqtant/util/exceptions.py
oqtant/util/server.py
oqtant-3.3.4.dist-info/LICENSE
oqtant-3.3.4.dist-info/METADATA
oqtant-3.3.4.dist-info/WHEEL
oqtant-3.3.4.dist-info/RECORD
