Metadata-Version: 2.1
Name: oqtant
Version: 3.3.4
Summary: Oqtant Desktop Suite
Home-page: https://oqtant.infleqtion.com/
License: Apache-2.0
Author: Larry Buza
Author-email: lawrence.buza@coldquanta.com
Requires-Python: >=3.10,<3.12
Classifier: License :: OSI Approved :: Apache Software License
Classifier: Operating System :: OS Independent
Classifier: Programming Language :: Python :: 3
Classifier: Programming Language :: Python :: 3.10
Classifier: Programming Language :: Python :: 3.11
Requires-Dist: bert-schemas (>=4.6.0,<5.0.0)
Requires-Dist: click (>=8.1.7,<9.0.0)
Requires-Dist: fastapi (>=0.103.1,<0.104.0)
Requires-Dist: ipyauth (>=0.2.6,<0.3.0)
Requires-Dist: ipykernel (>=6.23.1,<7.0.0)
Requires-Dist: ipywidgets (>=7.6.5,<8.0.0)
Requires-Dist: killport (>=1.2.0,<2.0.0)
Requires-Dist: matplotlib (>=3.6.2,<3.7.0)
Requires-Dist: notebook (>=6.4.12,<7.0.0)
Requires-Dist: numpy (>=1.23.2,<2.0.0)
Requires-Dist: pydantic (>=2.3.0,<3.0.0)
Requires-Dist: pydantic-settings (>=2.0.3,<3.0.0)
Requires-Dist: pyjwt (>=2.8.0,<3.0.0)
Requires-Dist: requests (>=2.28.1,<3.0.0)
Requires-Dist: scipy (==1.10.0)
Requires-Dist: semver (>=3.0.0,<4.0.0)
Requires-Dist: tabulate (>=0.9.0,<0.10.0)
Requires-Dist: traitlets (==5.9.0)
Requires-Dist: urllib3 (>=1.26.12,<2.0.0)
Requires-Dist: uvicorn[standard] (>=0.20.0,<0.21.0)
Project-URL: Repository, https://gitlab.com/infleqtion/albert/oqtant
